[{"Name":"Carlitos","UID":"67127224","Age":"33","Height":"5'10\"","Media Description":"Experienced striker","NoB":"ESP","Position":"AM (C), ST (C)","Personality":"Balanced","Left Foot":"Fairly Strong","Right Foot":"Very Strong","Hierarchy":"Influential Player","Social Groups":"Others","Weight":"156 lbs","Acc":"11","Agg":"7","Agi":"13","Bal":"12","Cor":"12","Cro":"13","Dri":"14","Fin":"15","Fir":"15","Fre":"14","Hea":"8","Jum":"8","Kic":"3","Lon":"12","L Th":"6","Mar":"5","Nat":"11","OtB":"13","Pac":"11","Pas":"13","Pen":"12","Pos":"6","Sta":"11","Str":"10","Tck":"6","Tec":"15","Thr":"3","Aer":"2","Ant":"13","Bra":"8","Cmd":"1","Com":"1","Cmp":"14","Cnt":"10","Dec":"12","Det":"9","Ecc":"1","Fla":"15","Han":"1","Ldr":"10","1v1":"1","Pun":"1","Ref":"2","TRO":"1","Tea":"9","Vis":"12","Wor":"10","Salary":"$326,000 p/a","Expires":"6/30/2025","analysis":"- Excellent Dribbler (Dribbling: 14, Flair: 15, Technique: 15)\n- Great Finisher (Finishing: 15)\n- Very Good First Touch (First Touch: 15)\n- Good set-piece taker (Free Kick Taking: 14, Corners: 12, Penalty Taking: 12)\n- Incapable Defender (Marking: 5, Tackling: 6, Positioning: 6)\n- Composed Player (Composure: 14)\n- Poor Teamwork & Work Ethic (Teamwork: 9, Work Rate: 10, Determination: 9)\n- Lacking Physicality (Jumping Reach: 8, Strength: 10, Heading: 8)"},{"Name":"Nikos Tsoukalos","UID":"36060292","Age":"31","Height":"6'0\"","Media Description":"Striker","NoB":"GRE","Position":"AM (LC), ST (C)","Personality":"Balanced","Left Foot":"Very Strong","Right Foot":"Weak","Hierarchy":"Highly Influential Player","Social Groups":"Core Social Group","Weight":"171 lbs","Acc":"12","Agg":"11","Agi":"11","Bal":"8","Cor":"5","Cro":"9","Dri":"10","Fin":"12","Fir":"11","Fre":"8","Hea":"12","Jum":"12","Kic":"3","Lon":"11","L Th":"7","Mar":"8","Nat":"11","OtB":"12","Pac":"13","Pas":"11","Pen":"9","Pos":"10","Sta":"11","Str":"6","Tck":"9","Tec":"12","Thr":"3","Aer":"1","Ant":"13","Bra":"10","Cmd":"1","Com":"1","Cmp":"12","Cnt":"10","Dec":"10","Det":"11","Ecc":"1","Fla":"11","Han":"2","Ldr":"8","1v1":"3","Pun":"2","Ref":"3","TRO":"2","Tea":"11","Vis":"12","Wor":"11","Salary":"$30,500 p/a","Expires":"6/30/2024","analysis":"- Balanced Technical Ability (Dribbling: 10, Finishing: 12, First Touch: 11, Technique: 12)\n- Limited Defending (Marking: 8, Tackling: 9, Positioning: 10)\n- Poor Stamina & Strength (Stamina: 11, Strength: 6, Balance: 8, Natural Fitness: 11)\n- Good Vision and Anticipation (Anticipation: 13, Vision: 12)\n- Decent Pace & Agility (Acceleration: 12, Pace: 13, Agility: 11)\n- Average Composure & Concentration (Composure: 12, Concentration: 10)\n- Good in the Air (Heading: 12, Jumping Reach: 12)"},{"Name":"Sotiris Tsiloulis","UID":"36097490","Age":"28","Height":"6'1\"","Media Description":"Winger","NoB":"GRE","Position":"AM (RLC), ST (C)","Personality":"Fairly Ambitious","Left Foot":"Weak","Right Foot":"Very Strong","Hierarchy":"Influential Player","Social Groups":"Core Social Group","Weight":"171 lbs","Acc":"13","Agg":"10","Agi":"12","Bal":"13","Cor":"10","Cro":"12","Dri":"14","Fin":"12","Fir":"13","Fre":"9","Hea":"13","Jum":"12","Kic":"2","Lon":"10","L Th":"6","Mar":"7","Nat":"12","OtB":"13","Pac":"13","Pas":"10","Pen":"12","Pos":"8","Sta":"12","Str":"12","Tck":"6","Tec":"14","Thr":"1","Aer":"3","Ant":"11","Bra":"8","Cmd":"3","Com":"3","Cmp":"9","Cnt":"8","Dec":"8","Det":"10","Ecc":"3","Fla":"12","Han":"3","Ldr":"7","1v1":"1","Pun":"3","Ref":"3","TRO":"3","Tea":"8","Vis":"9","Wor":"11","Salary":"$109,000 p/a","Expires":"6/30/2024","analysis":"- Skilled Dribbler (Dribbling: 14, Technique: 14, Flair: 12)\n- Very Poor Defending (Marking: 7, Tackling: 6, Positioning: 8)\n- Incapable Leader (Leadership: 7, Teamwork: 8)\n- Lacking Mental Strength (Bravery: 8, Composure: 9, Concentration: 8, Decisions: 8)\n- Poor Vision & Passing Ability (Passing: 10, Anticipation: 11, Vision: 9)\n- Above Average Physicality (Acceleration: 13, Agility: 12, Balance: 13, Jumping Reach: 12, Pace: 13, Stamina: 12, Strength: 12, Natural Fitness: 12)"},{"Name":"Flosard Malçi","UID":"36128999","Age":"28","Height":"5'11\"","Media Description":"Winger","NoB":"ALB","Position":"AM (RLC), ST (C)","Personality":"Fairly Ambitious","Left Foot":"Weak","Right Foot":"Very Strong","Hierarchy":"Other Players","Social Groups":"Secondary Social Group A","Weight":"167 lbs","Acc":"10","Agg":"8","Agi":"10","Bal":"12","Cor":"12","Cro":"12","Dri":"13","Fin":"12","Fir":"12","Fre":"13","Hea":"10","Jum":"10","Kic":"2","Lon":"12","L Th":"7","Mar":"6","Nat":"9","OtB":"12","Pac":"10","Pas":"9","Pen":"16","Pos":"9","Sta":"9","Str":"10","Tck":"7","Tec":"13","Thr":"2","Aer":"1","Ant":"9","Bra":"8","Cmd":"1","Com":"3","Cmp":"8","Cnt":"11","Dec":"9","Det":"6","Ecc":"3","Fla":"13","Han":"3","Ldr":"9","1v1":"2","Pun":"2","Ref":"2","TRO":"2","Tea":"9","Vis":"7","Wor":"10","Salary":"$15,500 p/a","Expires":"6/30/2024","analysis":"- Good Penalty Taker (Penalty Taking: 16)\n- Decent Dribbler & Flair Player (Dribbling: 13, Technique: 13, Flair: 13)\n- Limited Defending (Marking: 6, Tackling: 7, Positioning: 9)\n- Poor Passing Ability (Passing: 9, Anticipation: 9, Vision: 7, Decisions: 9)\n- Lacking Stamina (Natural Fitness: 9, Stamina: 9, Work Rate: 10, Determination: 6)\n- Poor Mental Fortitude (Bravery: 8, Aggression: 8, Composure: 8)\n- Poor Physical Abilities (Acceleration: 10, Agility: 10, Pace: 10)"},{"Name":"Alexandros Tereziou","UID":"36150308","Age":"23","Height":"5'11\"","Media Description":"Striker","NoB":"GRE","Position":"AM (L), ST (C)","Personality":"Ambitious","Left Foot":"Very Strong","Right Foot":"Weak","Hierarchy":"Other Players","Social Groups":"Secondary Social Group A","Weight":"167 lbs","Acc":"13","Agg":"11","Agi":"11","Bal":"2","Cor":"6","Cro":"8","Dri":"10","Fin":"13","Fir":"12","Fre":"6","Hea":"11","Jum":"10","Kic":"3","Lon":"7","L Th":"5","Mar":"5","Nat":"8","OtB":"9","Pac":"11","Pas":"10","Pen":"4","Pos":"5","Sta":"10","Str":"9","Tck":"5","Tec":"9","Thr":"3","Aer":"3","Ant":"11","Bra":"5","Cmd":"2","Com":"3","Cmp":"7","Cnt":"7","Dec":"6","Det":"6","Ecc":"2","Fla":"13","Han":"1","Ldr":"14","1v1":"3","Pun":"1","Ref":"2","TRO":"3","Tea":"6","Vis":"5","Wor":"10","Salary":"$15,500 p/a","Expires":"6/30/2024","analysis":"- Lacking Physical Balance (Balance: 2)\n- Poor Mental Attributes (Bravery: 5, Composure: 7, Concentration: 7, Decisions: 6, Determination: 6, Teamwork: 6, Vision: 5, Positioning: 5)\n- Decent Pace (Acceleration: 13, Pace: 11, Agility: 11)\n- Limited Strength, Stamina & Fitness (Strength: 9, Stamina: 10, Natural Fitness: 8)\n- Poor Defending Ability (Marking: 5, Tackling: 5, Positioning: 5)\n- Below average technical ability (Technique: 9, First Touch: 12, Dribbling: 10)"},{"Name":"Toshio Lake","UID":"37071186","Age":"22","Height":"5'10\"","Media Description":"Striker","NoB":"NED","Position":"AM (LC), ST (C)","Personality":"Balanced","Left Foot":"Weak","Right Foot":"Very Strong","Hierarchy":"Other Players","Social Groups":"Secondary Social Group B","Weight":"165 lbs","Acc":"15","Agg":"8","Agi":"13","Bal":"11","Cor":"7","Cro":"11","Dri":"10","Fin":"10","Fir":"12","Fre":"8","Hea":"9","Jum":"5","Kic":"1","Lon":"11","L Th":"5","Mar":"8","Nat":"7","OtB":"11","Pac":"15","Pas":"12","Pen":"4","Pos":"5","Sta":"7","Str":"12","Tck":"7","Tec":"11","Thr":"2","Aer":"1","Ant":"10","Bra":"4","Cmd":"3","Com":"3","Cmp":"10","Cnt":"10","Dec":"12","Det":"9","Ecc":"4","Fla":"8","Han":"2","Ldr":"9","1v1":"1","Pun":"2","Ref":"3","TRO":"1","Tea":"9","Vis":"7","Wor":"8","Salary":"$69,000 p/a","Expires":"6/30/2024","analysis":"- Very Quick (Acceleration: 15, Pace: 15)\n- Technically Inept (Dribbling: 10, First Touch: 12, Technique: 11)\n- Poor Defensive Attributes (Marking: 8, Tackling: 7, Positioning: 5)\n- Lacks Stamina & Fitness (Natural Fitness: 7, Stamina: 7)\n- Easily Intimidated (Bravery: 4, Aggression: 8)\n- Poor Vision & Judgement (Vision: 7, Decisions: 12)\n- No Aerial Presence (Heading: 9, Jumping Reach: 5)"}]